<?xml version="1.0" ?>
<AddOn xmlns="http://umlfri.org/xmlschema/addon.xsd">
    <Identity uri="urn:umlfri.org:examples:patchExample" />
    
    <FriendlyName name="Patch plugin for gestures" version="0.1" />
    <Author>
        <Name name="Peter Pajta" />
        <Homepage url="http://umlfri.org" />
        
        <CommonLicense name="GPL-2" />
    </Author>
    
    <Icon path="icons/testTubes.png" />
    
    <Description>
		Patch plugin for gestures.
    </Description>
    
    <Plugin>
        <Patch module="plugin" />
    </Plugin>
</AddOn>
